httpCRUDUtils/__init__.py
httpCRUDUtils/client.py
httpCRUDUtils/utils.py
tests/__init__.py
tests/test.py
http_crud_sdk-1.0.0.dist-info/METADATA
http_crud_sdk-1.0.0.dist-info/WHEEL
http_crud_sdk-1.0.0.dist-info/top_level.txt
http_crud_sdk-1.0.0.dist-info/RECORD
