Metadata-Version: 2.1
Name: http-crud-sdk
Version: 1.0.0
Summary: A great CRUD SDK
Home-page: https://github.com/LEstevalor/HttpCRUDUtils
Author: LEstevalor
Author-email: 25348891955@qq.com
License: UNKNOWN
Platform: UNKNOWN
Classifier: Development Status :: 3 - Alpha
Classifier: Intended Audience :: Developers
Classifier: License :: OSI Approved :: MIT License
Classifier: Programming Language :: Python :: 3
Classifier: Programming Language :: Python :: 3.6
Classifier: Programming Language :: Python :: 3.7
Classifier: Programming Language :: Python :: 3.8
Requires-Dist: requests
